[
    {
        "id": 1,
        "turbine_id": 1,
        "inspected_at": "2022-03-05T16:00:00.000Z",
        "created_at": "2024-01-27T12:55:00Z",
        "updated_at": "2024-01-27T13:00:00Z"
    },
    {
        "id": 2,
        "turbine_id": 1,
        "inspected_at": "2022-08-12T13:00:00.000Z",
        "created_at": "2024-01-27T12:55:00Z",
        "updated_at": "2024-01-27T13:00:00Z"
    },
    {
        "id": 3,
        "turbine_id": 2,
        "inspected_at": "2022-06-14T13:00:00.000Z",
        "created_at": "2024-01-27T12:55:00Z",
        "updated_at": "2024-01-27T13:00:00Z"
    },
    {
        "id": 4,
        "turbine_id": 2,
        "inspected_at": "2023-01-05T09:00:00.000Z",
        "created_at": "2024-01-27T12:55:00Z",
        "updated_at": "2024-01-27T13:00:00Z"
    },
    {
        "id": 5,
        "turbine_id": 3,
        "inspected_at": "2023-12-20T12:00:00.000Z",
        "created_at": "2024-01-27T12:55:00Z",
        "updated_at": "2024-01-27T13:00:00Z"
    },
    {
        "id": 6,
        "turbine_id": 4,
        "inspected_at": "2024-01-28T09:00:00.000Z",
        "created_at": "2024-01-27T12:55:00Z",
        "updated_at": "2024-01-27T13:00:00Z"
    },
    {
        "id": 7,
        "turbine_id": 4,
        "inspected_at": "2022-02-19T11:00:00.000Z",
        "created_at": "2024-01-27T12:55:00Z",
        "updated_at": "2024-01-27T13:00:00Z"
    },
    {
        "id": 8,
        "turbine_id": 4,
        "inspected_at": "2023-08-26T10:00:00.000Z",
        "created_at": "2024-01-27T12:55:00Z",
        "updated_at": "2024-01-27T13:00:00Z"
    },
    {
        "id": 9,
        "turbine_id": 5,
        "inspected_at": "2024-01-14T12:00:00.000Z",
        "created_at": "2024-01-27T12:55:00Z",
        "updated_at": "2024-01-27T13:00:00Z"
    },
    {
        "id": 10,
        "turbine_id": 5,
        "inspected_at": "2023-01-26T14:00:00.000Z",
        "created_at": "2024-01-27T12:55:00Z",
        "updated_at": "2024-01-27T13:00:00Z"
    },
    {
        "id": 11,
        "turbine_id": 6,
        "inspected_at": "2023-07-11T11:00:00.000Z",
        "created_at": "2024-01-27T12:55:00Z",
        "updated_at": "2024-01-27T13:00:00Z"
    },
    {
        "id": 12,
        "turbine_id": 6,
        "inspected_at": "2023-02-11T14:00:00.000Z",
        "created_at": "2024-01-27T12:55:00Z",
        "updated_at": "2024-01-27T13:00:00Z"
    },
    {
        "id": 13,
        "turbine_id": 7,
        "inspected_at": "2023-05-03T12:00:00.000Z",
        "created_at": "2024-01-27T12:55:00Z",
        "updated_at": "2024-01-27T13:00:00Z"
    },
    {
        "id": 14,
        "turbine_id": 8,
        "inspected_at": "2023-01-08T17:00:00.000Z",
        "created_at": "2024-01-27T12:55:00Z",
        "updated_at": "2024-01-27T13:00:00Z"
    },
    {
        "id": 15,
        "turbine_id": 9,
        "inspected_at": "2023-05-04T15:00:00.000Z",
        "created_at": "2024-01-27T12:55:00Z",
        "updated_at": "2024-01-27T13:00:00Z"
    },
    {
        "id": 16,
        "turbine_id": 9,
        "inspected_at": "2022-10-17T08:00:00.000Z",
        "created_at": "2024-01-27T12:55:00Z",
        "updated_at": "2024-01-27T13:00:00Z"
    },
    {
        "id": 17,
        "turbine_id": 10,
        "inspected_at": "2023-03-03T13:00:00.000Z",
        "created_at": "2024-01-27T12:55:00Z",
        "updated_at": "2024-01-27T13:00:00Z"
    },
    {
        "id": 18,
        "turbine_id": 11,
        "inspected_at": "2023-09-10T13:00:00.000Z",
        "created_at": "2024-01-27T12:55:00Z",
        "updated_at": "2024-01-27T13:00:00Z"
    },
    {
        "id": 19,
        "turbine_id": 12,
        "inspected_at": "2023-11-20T12:00:00.000Z",
        "created_at": "2024-01-27T12:55:00Z",
        "updated_at": "2024-01-27T13:00:00Z"
    },
    {
        "id": 20,
        "turbine_id": 12,
        "inspected_at": "2023-05-27T15:00:00.000Z",
        "created_at": "2024-01-27T12:55:00Z",
        "updated_at": "2024-01-27T13:00:00Z"
    },
    {
        "id": 21,
        "turbine_id": 12,
        "inspected_at": "2022-02-03T09:00:00.000Z",
        "created_at": "2024-01-27T12:55:00Z",
        "updated_at": "2024-01-27T13:00:00Z"
    },
    {
        "id": 22,
        "turbine_id": 13,
        "inspected_at": "2023-07-24T16:00:00.000Z",
        "created_at": "2024-01-27T12:55:00Z",
        "updated_at": "2024-01-27T13:00:00Z"
    },
    {
        "id": 23,
        "turbine_id": 13,
        "inspected_at": "2023-11-08T10:00:00.000Z",
        "created_at": "2024-01-27T12:55:00Z",
        "updated_at": "2024-01-27T13:00:00Z"
    },
    {
        "id": 24,
        "turbine_id": 14,
        "inspected_at": "2023-12-07T17:00:00.000Z",
        "created_at": "2024-01-27T12:55:00Z",
        "updated_at": "2024-01-27T13:00:00Z"
    },
    {
        "id": 25,
        "turbine_id": 15,
        "inspected_at": "2023-08-07T12:00:00.000Z",
        "created_at": "2024-01-27T12:55:00Z",
        "updated_at": "2024-01-27T13:00:00Z"
    },
    {
        "id": 26,
        "turbine_id": 15,
        "inspected_at": "2023-04-09T08:00:00.000Z",
        "created_at": "2024-01-27T12:55:00Z",
        "updated_at": "2024-01-27T13:00:00Z"
    },
    {
        "id": 27,
        "turbine_id": 16,
        "inspected_at": "2022-10-27T08:00:00.000Z",
        "created_at": "2024-01-27T12:55:00Z",
        "updated_at": "2024-01-27T13:00:00Z"
    },
    {
        "id": 28,
        "turbine_id": 16,
        "inspected_at": "2022-05-11T12:00:00.000Z",
        "created_at": "2024-01-27T12:55:00Z",
        "updated_at": "2024-01-27T13:00:00Z"
    },
    {
        "id": 29,
        "turbine_id": 16,
        "inspected_at": "2023-12-11T14:00:00.000Z",
        "created_at": "2024-01-27T12:55:00Z",
        "updated_at": "2024-01-27T13:00:00Z"
    },
    {
        "id": 30,
        "turbine_id": 17,
        "inspected_at": "2022-11-05T09:00:00.000Z",
        "created_at": "2024-01-27T12:55:00Z",
        "updated_at": "2024-01-27T13:00:00Z"
    },
    {
        "id": 31,
        "turbine_id": 18,
        "inspected_at": "2022-04-12T16:00:00.000Z",
        "created_at": "2024-01-27T12:55:00Z",
        "updated_at": "2024-01-27T13:00:00Z"
    },
    {
        "id": 32,
        "turbine_id": 18,
        "inspected_at": "2023-05-01T13:00:00.000Z",
        "created_at": "2024-01-27T12:55:00Z",
        "updated_at": "2024-01-27T13:00:00Z"
    },
    {
        "id": 33,
        "turbine_id": 19,
        "inspected_at": "2023-09-04T12:00:00.000Z",
        "created_at": "2024-01-27T12:55:00Z",
        "updated_at": "2024-01-27T13:00:00Z"
    },
    {
        "id": 34,
        "turbine_id": 19,
        "inspected_at": "2022-10-08T15:00:00.000Z",
        "created_at": "2024-01-27T12:55:00Z",
        "updated_at": "2024-01-27T13:00:00Z"
    },
    {
        "id": 35,
        "turbine_id": 20,
        "inspected_at": "2022-03-29T15:00:00.000Z",
        "created_at": "2024-01-27T12:55:00Z",
        "updated_at": "2024-01-27T13:00:00Z"
    },
    {
        "id": 36,
        "turbine_id": 21,
        "inspected_at": "2022-03-20T15:00:00.000Z",
        "created_at": "2024-01-27T12:55:00Z",
        "updated_at": "2024-01-27T13:00:00Z"
    },
    {
        "id": 37,
        "turbine_id": 21,
        "inspected_at": "2023-03-13T11:00:00.000Z",
        "created_at": "2024-01-27T12:55:00Z",
        "updated_at": "2024-01-27T13:00:00Z"
    },
    {
        "id": 38,
        "turbine_id": 21,
        "inspected_at": "2022-12-23T16:00:00.000Z",
        "created_at": "2024-01-27T12:55:00Z",
        "updated_at": "2024-01-27T13:00:00Z"
    },
    {
        "id": 39,
        "turbine_id": 22,
        "inspected_at": "2023-06-13T15:00:00.000Z",
        "created_at": "2024-01-27T12:55:00Z",
        "updated_at": "2024-01-27T13:00:00Z"
    },
    {
        "id": 40,
        "turbine_id": 22,
        "inspected_at": "2023-12-19T09:00:00.000Z",
        "created_at": "2024-01-27T12:55:00Z",
        "updated_at": "2024-01-27T13:00:00Z"
    },
    {
        "id": 41,
        "turbine_id": 22,
        "inspected_at": "2022-08-26T14:00:00.000Z",
        "created_at": "2024-01-27T12:55:00Z",
        "updated_at": "2024-01-27T13:00:00Z"
    },
    {
        "id": 42,
        "turbine_id": 23,
        "inspected_at": "2023-03-29T15:00:00.000Z",
        "created_at": "2024-01-27T12:55:00Z",
        "updated_at": "2024-01-27T13:00:00Z"
    },
    {
        "id": 43,
        "turbine_id": 23,
        "inspected_at": "2022-11-15T11:00:00.000Z",
        "created_at": "2024-01-27T12:55:00Z",
        "updated_at": "2024-01-27T13:00:00Z"
    },
    {
        "id": 44,
        "turbine_id": 24,
        "inspected_at": "2023-11-06T13:00:00.000Z",
        "created_at": "2024-01-27T12:55:00Z",
        "updated_at": "2024-01-27T13:00:00Z"
    },
    {
        "id": 45,
        "turbine_id": 25,
        "inspected_at": "2023-02-26T16:00:00.000Z",
        "created_at": "2024-01-27T12:55:00Z",
        "updated_at": "2024-01-27T13:00:00Z"
    },
    {
        "id": 46,
        "turbine_id": 25,
        "inspected_at": "2023-02-05T10:00:00.000Z",
        "created_at": "2024-01-27T12:55:00Z",
        "updated_at": "2024-01-27T13:00:00Z"
    },
    {
        "id": 47,
        "turbine_id": 26,
        "inspected_at": "2023-08-13T10:00:00.000Z",
        "created_at": "2024-01-27T12:55:00Z",
        "updated_at": "2024-01-27T13:00:00Z"
    },
    {
        "id": 48,
        "turbine_id": 27,
        "inspected_at": "2023-10-19T12:00:00.000Z",
        "created_at": "2024-01-27T12:55:00Z",
        "updated_at": "2024-01-27T13:00:00Z"
    },
    {
        "id": 49,
        "turbine_id": 28,
        "inspected_at": "2023-10-12T12:00:00.000Z",
        "created_at": "2024-01-27T12:55:00Z",
        "updated_at": "2024-01-27T13:00:00Z"
    },
    {
        "id": 50,
        "turbine_id": 29,
        "inspected_at": "2023-03-09T15:00:00.000Z",
        "created_at": "2024-01-27T12:55:00Z",
        "updated_at": "2024-01-27T13:00:00Z"
    },
    {
        "id": 51,
        "turbine_id": 29,
        "inspected_at": "2023-06-08T10:00:00.000Z",
        "created_at": "2024-01-27T12:55:00Z",
        "updated_at": "2024-01-27T13:00:00Z"
    },
    {
        "id": 52,
        "turbine_id": 29,
        "inspected_at": "2023-12-19T10:00:00.000Z",
        "created_at": "2024-01-27T12:55:00Z",
        "updated_at": "2024-01-27T13:00:00Z"
    },
    {
        "id": 53,
        "turbine_id": 30,
        "inspected_at": "2022-07-06T12:00:00.000Z",
        "created_at": "2024-01-27T12:55:00Z",
        "updated_at": "2024-01-27T13:00:00Z"
    },
    {
        "id": 54,
        "turbine_id": 31,
        "inspected_at": "2022-06-12T12:00:00.000Z",
        "created_at": "2024-01-27T12:55:00Z",
        "updated_at": "2024-01-27T13:00:00Z"
    },
    {
        "id": 55,
        "turbine_id": 32,
        "inspected_at": "2023-09-25T12:00:00.000Z",
        "created_at": "2024-01-27T12:55:00Z",
        "updated_at": "2024-01-27T13:00:00Z"
    },
    {
        "id": 56,
        "turbine_id": 32,
        "inspected_at": "2023-11-04T13:00:00.000Z",
        "created_at": "2024-01-27T12:55:00Z",
        "updated_at": "2024-01-27T13:00:00Z"
    },
    {
        "id": 57,
        "turbine_id": 33,
        "inspected_at": "2023-02-05T16:00:00.000Z",
        "created_at": "2024-01-27T12:55:00Z",
        "updated_at": "2024-01-27T13:00:00Z"
    },
    {
        "id": 58,
        "turbine_id": 33,
        "inspected_at": "2023-04-22T10:00:00.000Z",
        "created_at": "2024-01-27T12:55:00Z",
        "updated_at": "2024-01-27T13:00:00Z"
    },
    {
        "id": 59,
        "turbine_id": 34,
        "inspected_at": "2023-03-26T16:00:00.000Z",
        "created_at": "2024-01-27T12:55:00Z",
        "updated_at": "2024-01-27T13:00:00Z"
    },
    {
        "id": 60,
        "turbine_id": 34,
        "inspected_at": "2022-04-14T13:00:00.000Z",
        "created_at": "2024-01-27T12:55:00Z",
        "updated_at": "2024-01-27T13:00:00Z"
    },
    {
        "id": 61,
        "turbine_id": 35,
        "inspected_at": "2023-07-25T08:00:00.000Z",
        "created_at": "2024-01-27T12:55:00Z",
        "updated_at": "2024-01-27T13:00:00Z"
    },
    {
        "id": 62,
        "turbine_id": 36,
        "inspected_at": "2023-02-08T16:00:00.000Z",
        "created_at": "2024-01-27T12:55:00Z",
        "updated_at": "2024-01-27T13:00:00Z"
    },
    {
        "id": 63,
        "turbine_id": 36,
        "inspected_at": "2023-04-11T09:00:00.000Z",
        "created_at": "2024-01-27T12:55:00Z",
        "updated_at": "2024-01-27T13:00:00Z"
    },
    {
        "id": 64,
        "turbine_id": 36,
        "inspected_at": "2022-02-21T16:00:00.000Z",
        "created_at": "2024-01-27T12:55:00Z",
        "updated_at": "2024-01-27T13:00:00Z"
    },
    {
        "id": 65,
        "turbine_id": 37,
        "inspected_at": "2023-11-14T15:00:00.000Z",
        "created_at": "2024-01-27T12:55:00Z",
        "updated_at": "2024-01-27T13:00:00Z"
    },
    {
        "id": 66,
        "turbine_id": 37,
        "inspected_at": "2024-01-26T14:00:00.000Z",
        "created_at": "2024-01-27T12:55:00Z",
        "updated_at": "2024-01-27T13:00:00Z"
    },
    {
        "id": 67,
        "turbine_id": 38,
        "inspected_at": "2022-03-02T14:00:00.000Z",
        "created_at": "2024-01-27T12:55:00Z",
        "updated_at": "2024-01-27T13:00:00Z"
    },
    {
        "id": 68,
        "turbine_id": 38,
        "inspected_at": "2023-04-18T15:00:00.000Z",
        "created_at": "2024-01-27T12:55:00Z",
        "updated_at": "2024-01-27T13:00:00Z"
    },
    {
        "id": 69,
        "turbine_id": 38,
        "inspected_at": "2023-03-25T12:00:00.000Z",
        "created_at": "2024-01-27T12:55:00Z",
        "updated_at": "2024-01-27T13:00:00Z"
    },
    {
        "id": 70,
        "turbine_id": 39,
        "inspected_at": "2023-06-18T12:00:00.000Z",
        "created_at": "2024-01-27T12:55:00Z",
        "updated_at": "2024-01-27T13:00:00Z"
    },
    {
        "id": 71,
        "turbine_id": 39,
        "inspected_at": "2022-10-02T16:00:00.000Z",
        "created_at": "2024-01-27T12:55:00Z",
        "updated_at": "2024-01-27T13:00:00Z"
    },
    {
        "id": 72,
        "turbine_id": 39,
        "inspected_at": "2022-07-06T08:00:00.000Z",
        "created_at": "2024-01-27T12:55:00Z",
        "updated_at": "2024-01-27T13:00:00Z"
    },
    {
        "id": 73,
        "turbine_id": 40,
        "inspected_at": "2022-03-10T15:00:00.000Z",
        "created_at": "2024-01-27T12:55:00Z",
        "updated_at": "2024-01-27T13:00:00Z"
    },
    {
        "id": 74,
        "turbine_id": 40,
        "inspected_at": "2022-10-05T13:00:00.000Z",
        "created_at": "2024-01-27T12:55:00Z",
        "updated_at": "2024-01-27T13:00:00Z"
    },
    {
        "id": 75,
        "turbine_id": 41,
        "inspected_at": "2023-02-12T11:00:00.000Z",
        "created_at": "2024-01-27T12:55:00Z",
        "updated_at": "2024-01-27T13:00:00Z"
    },
    {
        "id": 76,
        "turbine_id": 41,
        "inspected_at": "2023-10-29T16:00:00.000Z",
        "created_at": "2024-01-27T12:55:00Z",
        "updated_at": "2024-01-27T13:00:00Z"
    },
    {
        "id": 77,
        "turbine_id": 42,
        "inspected_at": "2022-10-12T15:00:00.000Z",
        "created_at": "2024-01-27T12:55:00Z",
        "updated_at": "2024-01-27T13:00:00Z"
    },
    {
        "id": 78,
        "turbine_id": 42,
        "inspected_at": "2022-02-11T16:00:00.000Z",
        "created_at": "2024-01-27T12:55:00Z",
        "updated_at": "2024-01-27T13:00:00Z"
    },
    {
        "id": 79,
        "turbine_id": 43,
        "inspected_at": "2023-03-15T13:00:00.000Z",
        "created_at": "2024-01-27T12:55:00Z",
        "updated_at": "2024-01-27T13:00:00Z"
    },
    {
        "id": 80,
        "turbine_id": 43,
        "inspected_at": "2023-04-25T12:00:00.000Z",
        "created_at": "2024-01-27T12:55:00Z",
        "updated_at": "2024-01-27T13:00:00Z"
    },
    {
        "id": 81,
        "turbine_id": 43,
        "inspected_at": "2023-12-15T13:00:00.000Z",
        "created_at": "2024-01-27T12:55:00Z",
        "updated_at": "2024-01-27T13:00:00Z"
    },
    {
        "id": 82,
        "turbine_id": 44,
        "inspected_at": "2023-10-20T15:00:00.000Z",
        "created_at": "2024-01-27T12:55:00Z",
        "updated_at": "2024-01-27T13:00:00Z"
    },
    {
        "id": 83,
        "turbine_id": 44,
        "inspected_at": "2022-09-21T11:00:00.000Z",
        "created_at": "2024-01-27T12:55:00Z",
        "updated_at": "2024-01-27T13:00:00Z"
    },
    {
        "id": 84,
        "turbine_id": 45,
        "inspected_at": "2022-02-25T11:00:00.000Z",
        "created_at": "2024-01-27T12:55:00Z",
        "updated_at": "2024-01-27T13:00:00Z"
    },
    {
        "id": 85,
        "turbine_id": 45,
        "inspected_at": "2022-02-24T12:00:00.000Z",
        "created_at": "2024-01-27T12:55:00Z",
        "updated_at": "2024-01-27T13:00:00Z"
    },
    {
        "id": 86,
        "turbine_id": 46,
        "inspected_at": "2022-02-21T09:00:00.000Z",
        "created_at": "2024-01-27T12:55:00Z",
        "updated_at": "2024-01-27T13:00:00Z"
    },
    {
        "id": 87,
        "turbine_id": 46,
        "inspected_at": "2022-11-04T15:00:00.000Z",
        "created_at": "2024-01-27T12:55:00Z",
        "updated_at": "2024-01-27T13:00:00Z"
    },
    {
        "id": 88,
        "turbine_id": 46,
        "inspected_at": "2023-02-22T12:00:00.000Z",
        "created_at": "2024-01-27T12:55:00Z",
        "updated_at": "2024-01-27T13:00:00Z"
    },
    {
        "id": 89,
        "turbine_id": 47,
        "inspected_at": "2022-10-22T15:00:00.000Z",
        "created_at": "2024-01-27T12:55:00Z",
        "updated_at": "2024-01-27T13:00:00Z"
    },
    {
        "id": 90,
        "turbine_id": 47,
        "inspected_at": "2022-05-23T15:00:00.000Z",
        "created_at": "2024-01-27T12:55:00Z",
        "updated_at": "2024-01-27T13:00:00Z"
    },
    {
        "id": 91,
        "turbine_id": 47,
        "inspected_at": "2024-01-18T09:00:00.000Z",
        "created_at": "2024-01-27T12:55:00Z",
        "updated_at": "2024-01-27T13:00:00Z"
    },
    {
        "id": 92,
        "turbine_id": 48,
        "inspected_at": "2023-04-17T15:00:00.000Z",
        "created_at": "2024-01-27T12:55:00Z",
        "updated_at": "2024-01-27T13:00:00Z"
    },
    {
        "id": 93,
        "turbine_id": 48,
        "inspected_at": "2022-04-20T10:00:00.000Z",
        "created_at": "2024-01-27T12:55:00Z",
        "updated_at": "2024-01-27T13:00:00Z"
    },
    {
        "id": 94,
        "turbine_id": 48,
        "inspected_at": "2023-03-31T16:00:00.000Z",
        "created_at": "2024-01-27T12:55:00Z",
        "updated_at": "2024-01-27T13:00:00Z"
    },
    {
        "id": 95,
        "turbine_id": 49,
        "inspected_at": "2023-11-28T17:00:00.000Z",
        "created_at": "2024-01-27T12:55:00Z",
        "updated_at": "2024-01-27T13:00:00Z"
    },
    {
        "id": 96,
        "turbine_id": 49,
        "inspected_at": "2023-01-05T17:00:00.000Z",
        "created_at": "2024-01-27T12:55:00Z",
        "updated_at": "2024-01-27T13:00:00Z"
    },
    {
        "id": 97,
        "turbine_id": 49,
        "inspected_at": "2023-07-08T16:00:00.000Z",
        "created_at": "2024-01-27T12:55:00Z",
        "updated_at": "2024-01-27T13:00:00Z"
    },
    {
        "id": 98,
        "turbine_id": 50,
        "inspected_at": "2022-09-30T09:00:00.000Z",
        "created_at": "2024-01-27T12:55:00Z",
        "updated_at": "2024-01-27T13:00:00Z"
    },
    {
        "id": 99,
        "turbine_id": 50,
        "inspected_at": "2023-09-16T16:00:00.000Z",
        "created_at": "2024-01-27T12:55:00Z",
        "updated_at": "2024-01-27T13:00:00Z"
    },
    {
        "id": 100,
        "turbine_id": 51,
        "inspected_at": "2022-04-29T16:00:00.000Z",
        "created_at": "2024-01-27T12:55:00Z",
        "updated_at": "2024-01-27T13:00:00Z"
    },
    {
        "id": 101,
        "turbine_id": 51,
        "inspected_at": "2024-01-07T12:00:00.000Z",
        "created_at": "2024-01-27T12:55:00Z",
        "updated_at": "2024-01-27T13:00:00Z"
    },
    {
        "id": 102,
        "turbine_id": 52,
        "inspected_at": "2022-10-13T09:00:00.000Z",
        "created_at": "2024-01-27T12:55:00Z",
        "updated_at": "2024-01-27T13:00:00Z"
    },
    {
        "id": 103,
        "turbine_id": 52,
        "inspected_at": "2022-04-10T14:00:00.000Z",
        "created_at": "2024-01-27T12:55:00Z",
        "updated_at": "2024-01-27T13:00:00Z"
    },
    {
        "id": 104,
        "turbine_id": 52,
        "inspected_at": "2023-08-25T09:00:00.000Z",
        "created_at": "2024-01-27T12:55:00Z",
        "updated_at": "2024-01-27T13:00:00Z"
    },
    {
        "id": 105,
        "turbine_id": 53,
        "inspected_at": "2022-04-06T08:00:00.000Z",
        "created_at": "2024-01-27T12:55:00Z",
        "updated_at": "2024-01-27T13:00:00Z"
    },
    {
        "id": 106,
        "turbine_id": 54,
        "inspected_at": "2023-07-13T14:00:00.000Z",
        "created_at": "2024-01-27T12:55:00Z",
        "updated_at": "2024-01-27T13:00:00Z"
    },
    {
        "id": 107,
        "turbine_id": 55,
        "inspected_at": "2022-11-30T11:00:00.000Z",
        "created_at": "2024-01-27T12:55:00Z",
        "updated_at": "2024-01-27T13:00:00Z"
    },
    {
        "id": 108,
        "turbine_id": 56,
        "inspected_at": "2023-06-18T09:00:00.000Z",
        "created_at": "2024-01-27T12:55:00Z",
        "updated_at": "2024-01-27T13:00:00Z"
    },
    {
        "id": 109,
        "turbine_id": 57,
        "inspected_at": "2023-05-25T14:00:00.000Z",
        "created_at": "2024-01-27T12:55:00Z",
        "updated_at": "2024-01-27T13:00:00Z"
    },
    {
        "id": 110,
        "turbine_id": 57,
        "inspected_at": "2022-10-28T09:00:00.000Z",
        "created_at": "2024-01-27T12:55:00Z",
        "updated_at": "2024-01-27T13:00:00Z"
    },
    {
        "id": 111,
        "turbine_id": 58,
        "inspected_at": "2023-07-18T11:00:00.000Z",
        "created_at": "2024-01-27T12:55:00Z",
        "updated_at": "2024-01-27T13:00:00Z"
    },
    {
        "id": 112,
        "turbine_id": 59,
        "inspected_at": "2022-02-25T12:00:00.000Z",
        "created_at": "2024-01-27T12:55:00Z",
        "updated_at": "2024-01-27T13:00:00Z"
    },
    {
        "id": 113,
        "turbine_id": 60,
        "inspected_at": "2023-10-20T11:00:00.000Z",
        "created_at": "2024-01-27T12:55:00Z",
        "updated_at": "2024-01-27T13:00:00Z"
    },
    {
        "id": 114,
        "turbine_id": 60,
        "inspected_at": "2023-07-26T12:00:00.000Z",
        "created_at": "2024-01-27T12:55:00Z",
        "updated_at": "2024-01-27T13:00:00Z"
    },
    {
        "id": 115,
        "turbine_id": 60,
        "inspected_at": "2022-12-12T14:00:00.000Z",
        "created_at": "2024-01-27T12:55:00Z",
        "updated_at": "2024-01-27T13:00:00Z"
    },
    {
        "id": 116,
        "turbine_id": 61,
        "inspected_at": "2023-12-12T12:00:00.000Z",
        "created_at": "2024-01-27T12:55:00Z",
        "updated_at": "2024-01-27T13:00:00Z"
    },
    {
        "id": 117,
        "turbine_id": 61,
        "inspected_at": "2022-03-02T13:00:00.000Z",
        "created_at": "2024-01-27T12:55:00Z",
        "updated_at": "2024-01-27T13:00:00Z"
    },
    {
        "id": 118,
        "turbine_id": 61,
        "inspected_at": "2023-04-27T16:00:00.000Z",
        "created_at": "2024-01-27T12:55:00Z",
        "updated_at": "2024-01-27T13:00:00Z"
    },
    {
        "id": 119,
        "turbine_id": 62,
        "inspected_at": "2023-02-15T17:00:00.000Z",
        "created_at": "2024-01-27T12:55:00Z",
        "updated_at": "2024-01-27T13:00:00Z"
    },
    {
        "id": 120,
        "turbine_id": 63,
        "inspected_at": "2023-08-01T13:00:00.000Z",
        "created_at": "2024-01-27T12:55:00Z",
        "updated_at": "2024-01-27T13:00:00Z"
    },
    {
        "id": 121,
        "turbine_id": 63,
        "inspected_at": "2022-03-10T16:00:00.000Z",
        "created_at": "2024-01-27T12:55:00Z",
        "updated_at": "2024-01-27T13:00:00Z"
    },
    {
        "id": 122,
        "turbine_id": 63,
        "inspected_at": "2022-05-26T11:00:00.000Z",
        "created_at": "2024-01-27T12:55:00Z",
        "updated_at": "2024-01-27T13:00:00Z"
    },
    {
        "id": 123,
        "turbine_id": 64,
        "inspected_at": "2023-02-06T13:00:00.000Z",
        "created_at": "2024-01-27T12:55:00Z",
        "updated_at": "2024-01-27T13:00:00Z"
    },
    {
        "id": 124,
        "turbine_id": 65,
        "inspected_at": "2023-07-29T14:00:00.000Z",
        "created_at": "2024-01-27T12:55:00Z",
        "updated_at": "2024-01-27T13:00:00Z"
    },
    {
        "id": 125,
        "turbine_id": 66,
        "inspected_at": "2023-11-27T15:00:00.000Z",
        "created_at": "2024-01-27T12:55:00Z",
        "updated_at": "2024-01-27T13:00:00Z"
    },
    {
        "id": 126,
        "turbine_id": 67,
        "inspected_at": "2022-09-22T12:00:00.000Z",
        "created_at": "2024-01-27T12:55:00Z",
        "updated_at": "2024-01-27T13:00:00Z"
    },
    {
        "id": 127,
        "turbine_id": 67,
        "inspected_at": "2022-03-12T17:00:00.000Z",
        "created_at": "2024-01-27T12:55:00Z",
        "updated_at": "2024-01-27T13:00:00Z"
    },
    {
        "id": 128,
        "turbine_id": 68,
        "inspected_at": "2022-05-22T16:00:00.000Z",
        "created_at": "2024-01-27T12:55:00Z",
        "updated_at": "2024-01-27T13:00:00Z"
    },
    {
        "id": 129,
        "turbine_id": 69,
        "inspected_at": "2023-08-28T16:00:00.000Z",
        "created_at": "2024-01-27T12:55:00Z",
        "updated_at": "2024-01-27T13:00:00Z"
    },
    {
        "id": 130,
        "turbine_id": 69,
        "inspected_at": "2022-04-27T15:00:00.000Z",
        "created_at": "2024-01-27T12:55:00Z",
        "updated_at": "2024-01-27T13:00:00Z"
    },
    {
        "id": 131,
        "turbine_id": 69,
        "inspected_at": "2022-10-14T14:00:00.000Z",
        "created_at": "2024-01-27T12:55:00Z",
        "updated_at": "2024-01-27T13:00:00Z"
    },
    {
        "id": 132,
        "turbine_id": 70,
        "inspected_at": "2023-09-10T11:00:00.000Z",
        "created_at": "2024-01-27T12:55:00Z",
        "updated_at": "2024-01-27T13:00:00Z"
    },
    {
        "id": 133,
        "turbine_id": 71,
        "inspected_at": "2022-05-24T12:00:00.000Z",
        "created_at": "2024-01-27T12:55:00Z",
        "updated_at": "2024-01-27T13:00:00Z"
    },
    {
        "id": 134,
        "turbine_id": 71,
        "inspected_at": "2022-02-05T13:00:00.000Z",
        "created_at": "2024-01-27T12:55:00Z",
        "updated_at": "2024-01-27T13:00:00Z"
    },
    {
        "id": 135,
        "turbine_id": 72,
        "inspected_at": "2023-03-07T10:00:00.000Z",
        "created_at": "2024-01-27T12:55:00Z",
        "updated_at": "2024-01-27T13:00:00Z"
    },
    {
        "id": 136,
        "turbine_id": 72,
        "inspected_at": "2022-07-19T14:00:00.000Z",
        "created_at": "2024-01-27T12:55:00Z",
        "updated_at": "2024-01-27T13:00:00Z"
    },
    {
        "id": 137,
        "turbine_id": 73,
        "inspected_at": "2022-05-27T14:00:00.000Z",
        "created_at": "2024-01-27T12:55:00Z",
        "updated_at": "2024-01-27T13:00:00Z"
    },
    {
        "id": 138,
        "turbine_id": 74,
        "inspected_at": "2022-06-08T14:00:00.000Z",
        "created_at": "2024-01-27T12:55:00Z",
        "updated_at": "2024-01-27T13:00:00Z"
    },
    {
        "id": 139,
        "turbine_id": 75,
        "inspected_at": "2023-11-25T12:00:00.000Z",
        "created_at": "2024-01-27T12:55:00Z",
        "updated_at": "2024-01-27T13:00:00Z"
    },
    {
        "id": 140,
        "turbine_id": 75,
        "inspected_at": "2022-07-25T16:00:00.000Z",
        "created_at": "2024-01-27T12:55:00Z",
        "updated_at": "2024-01-27T13:00:00Z"
    },
    {
        "id": 141,
        "turbine_id": 76,
        "inspected_at": "2022-01-29T11:00:00.000Z",
        "created_at": "2024-01-27T12:55:00Z",
        "updated_at": "2024-01-27T13:00:00Z"
    },
    {
        "id": 142,
        "turbine_id": 76,
        "inspected_at": "2023-03-17T09:00:00.000Z",
        "created_at": "2024-01-27T12:55:00Z",
        "updated_at": "2024-01-27T13:00:00Z"
    },
    {
        "id": 143,
        "turbine_id": 77,
        "inspected_at": "2023-01-17T17:00:00.000Z",
        "created_at": "2024-01-27T12:55:00Z",
        "updated_at": "2024-01-27T13:00:00Z"
    },
    {
        "id": 144,
        "turbine_id": 78,
        "inspected_at": "2022-05-26T11:00:00.000Z",
        "created_at": "2024-01-27T12:55:00Z",
        "updated_at": "2024-01-27T13:00:00Z"
    },
    {
        "id": 145,
        "turbine_id": 79,
        "inspected_at": "2023-01-31T14:00:00.000Z",
        "created_at": "2024-01-27T12:55:00Z",
        "updated_at": "2024-01-27T13:00:00Z"
    },
    {
        "id": 146,
        "turbine_id": 79,
        "inspected_at": "2022-09-28T14:00:00.000Z",
        "created_at": "2024-01-27T12:55:00Z",
        "updated_at": "2024-01-27T13:00:00Z"
    },
    {
        "id": 147,
        "turbine_id": 79,
        "inspected_at": "2023-12-02T09:00:00.000Z",
        "created_at": "2024-01-27T12:55:00Z",
        "updated_at": "2024-01-27T13:00:00Z"
    },
    {
        "id": 148,
        "turbine_id": 80,
        "inspected_at": "2022-12-05T13:00:00.000Z",
        "created_at": "2024-01-27T12:55:00Z",
        "updated_at": "2024-01-27T13:00:00Z"
    },
    {
        "id": 149,
        "turbine_id": 80,
        "inspected_at": "2023-07-20T11:00:00.000Z",
        "created_at": "2024-01-27T12:55:00Z",
        "updated_at": "2024-01-27T13:00:00Z"
    },
    {
        "id": 150,
        "turbine_id": 81,
        "inspected_at": "2022-08-07T08:00:00.000Z",
        "created_at": "2024-01-27T12:55:00Z",
        "updated_at": "2024-01-27T13:00:00Z"
    },
    {
        "id": 151,
        "turbine_id": 81,
        "inspected_at": "2023-07-23T08:00:00.000Z",
        "created_at": "2024-01-27T12:55:00Z",
        "updated_at": "2024-01-27T13:00:00Z"
    },
    {
        "id": 152,
        "turbine_id": 82,
        "inspected_at": "2023-09-26T09:00:00.000Z",
        "created_at": "2024-01-27T12:55:00Z",
        "updated_at": "2024-01-27T13:00:00Z"
    },
    {
        "id": 153,
        "turbine_id": 83,
        "inspected_at": "2023-10-05T12:00:00.000Z",
        "created_at": "2024-01-27T12:55:00Z",
        "updated_at": "2024-01-27T13:00:00Z"
    },
    {
        "id": 154,
        "turbine_id": 84,
        "inspected_at": "2022-04-26T14:00:00.000Z",
        "created_at": "2024-01-27T12:55:00Z",
        "updated_at": "2024-01-27T13:00:00Z"
    },
    {
        "id": 155,
        "turbine_id": 84,
        "inspected_at": "2022-03-28T16:00:00.000Z",
        "created_at": "2024-01-27T12:55:00Z",
        "updated_at": "2024-01-27T13:00:00Z"
    },
    {
        "id": 156,
        "turbine_id": 84,
        "inspected_at": "2022-09-15T08:00:00.000Z",
        "created_at": "2024-01-27T12:55:00Z",
        "updated_at": "2024-01-27T13:00:00Z"
    },
    {
        "id": 157,
        "turbine_id": 85,
        "inspected_at": "2023-02-13T14:00:00.000Z",
        "created_at": "2024-01-27T12:55:00Z",
        "updated_at": "2024-01-27T13:00:00Z"
    },
    {
        "id": 158,
        "turbine_id": 85,
        "inspected_at": "2023-03-30T14:00:00.000Z",
        "created_at": "2024-01-27T12:55:00Z",
        "updated_at": "2024-01-27T13:00:00Z"
    },
    {
        "id": 159,
        "turbine_id": 85,
        "inspected_at": "2023-10-05T11:00:00.000Z",
        "created_at": "2024-01-27T12:55:00Z",
        "updated_at": "2024-01-27T13:00:00Z"
    },
    {
        "id": 160,
        "turbine_id": 86,
        "inspected_at": "2023-10-05T16:00:00.000Z",
        "created_at": "2024-01-27T12:55:00Z",
        "updated_at": "2024-01-27T13:00:00Z"
    },
    {
        "id": 161,
        "turbine_id": 87,
        "inspected_at": "2023-03-24T15:00:00.000Z",
        "created_at": "2024-01-27T12:55:00Z",
        "updated_at": "2024-01-27T13:00:00Z"
    },
    {
        "id": 162,
        "turbine_id": 87,
        "inspected_at": "2023-08-01T08:00:00.000Z",
        "created_at": "2024-01-27T12:55:00Z",
        "updated_at": "2024-01-27T13:00:00Z"
    },
    {
        "id": 163,
        "turbine_id": 87,
        "inspected_at": "2023-01-04T16:00:00.000Z",
        "created_at": "2024-01-27T12:55:00Z",
        "updated_at": "2024-01-27T13:00:00Z"
    },
    {
        "id": 164,
        "turbine_id": 88,
        "inspected_at": "2022-08-01T12:00:00.000Z",
        "created_at": "2024-01-27T12:55:00Z",
        "updated_at": "2024-01-27T13:00:00Z"
    },
    {
        "id": 165,
        "turbine_id": 89,
        "inspected_at": "2023-08-09T15:00:00.000Z",
        "created_at": "2024-01-27T12:55:00Z",
        "updated_at": "2024-01-27T13:00:00Z"
    },
    {
        "id": 166,
        "turbine_id": 90,
        "inspected_at": "2022-09-12T13:00:00.000Z",
        "created_at": "2024-01-27T12:55:00Z",
        "updated_at": "2024-01-27T13:00:00Z"
    },
    {
        "id": 167,
        "turbine_id": 90,
        "inspected_at": "2022-09-28T12:00:00.000Z",
        "created_at": "2024-01-27T12:55:00Z",
        "updated_at": "2024-01-27T13:00:00Z"
    },
    {
        "id": 168,
        "turbine_id": 91,
        "inspected_at": "2023-08-26T13:00:00.000Z",
        "created_at": "2024-01-27T12:55:00Z",
        "updated_at": "2024-01-27T13:00:00Z"
    },
    {
        "id": 169,
        "turbine_id": 91,
        "inspected_at": "2023-07-10T14:00:00.000Z",
        "created_at": "2024-01-27T12:55:00Z",
        "updated_at": "2024-01-27T13:00:00Z"
    },
    {
        "id": 170,
        "turbine_id": 92,
        "inspected_at": "2023-12-03T12:00:00.000Z",
        "created_at": "2024-01-27T12:55:00Z",
        "updated_at": "2024-01-27T13:00:00Z"
    },
    {
        "id": 171,
        "turbine_id": 92,
        "inspected_at": "2023-06-26T10:00:00.000Z",
        "created_at": "2024-01-27T12:55:00Z",
        "updated_at": "2024-01-27T13:00:00Z"
    },
    {
        "id": 172,
        "turbine_id": 92,
        "inspected_at": "2024-01-13T10:00:00.000Z",
        "created_at": "2024-01-27T12:55:00Z",
        "updated_at": "2024-01-27T13:00:00Z"
    },
    {
        "id": 173,
        "turbine_id": 93,
        "inspected_at": "2023-11-07T09:00:00.000Z",
        "created_at": "2024-01-27T12:55:00Z",
        "updated_at": "2024-01-27T13:00:00Z"
    },
    {
        "id": 174,
        "turbine_id": 93,
        "inspected_at": "2022-09-09T12:00:00.000Z",
        "created_at": "2024-01-27T12:55:00Z",
        "updated_at": "2024-01-27T13:00:00Z"
    },
    {
        "id": 175,
        "turbine_id": 93,
        "inspected_at": "2023-03-13T16:00:00.000Z",
        "created_at": "2024-01-27T12:55:00Z",
        "updated_at": "2024-01-27T13:00:00Z"
    },
    {
        "id": 176,
        "turbine_id": 94,
        "inspected_at": "2022-02-15T10:00:00.000Z",
        "created_at": "2024-01-27T12:55:00Z",
        "updated_at": "2024-01-27T13:00:00Z"
    },
    {
        "id": 177,
        "turbine_id": 94,
        "inspected_at": "2022-03-18T14:00:00.000Z",
        "created_at": "2024-01-27T12:55:00Z",
        "updated_at": "2024-01-27T13:00:00Z"
    },
    {
        "id": 178,
        "turbine_id": 95,
        "inspected_at": "2023-07-13T08:00:00.000Z",
        "created_at": "2024-01-27T12:55:00Z",
        "updated_at": "2024-01-27T13:00:00Z"
    },
    {
        "id": 179,
        "turbine_id": 95,
        "inspected_at": "2023-11-03T13:00:00.000Z",
        "created_at": "2024-01-27T12:55:00Z",
        "updated_at": "2024-01-27T13:00:00Z"
    },
    {
        "id": 180,
        "turbine_id": 96,
        "inspected_at": "2023-08-31T11:00:00.000Z",
        "created_at": "2024-01-27T12:55:00Z",
        "updated_at": "2024-01-27T13:00:00Z"
    },
    {
        "id": 181,
        "turbine_id": 97,
        "inspected_at": "2023-02-02T14:00:00.000Z",
        "created_at": "2024-01-27T12:55:00Z",
        "updated_at": "2024-01-27T13:00:00Z"
    },
    {
        "id": 182,
        "turbine_id": 97,
        "inspected_at": "2022-09-02T14:00:00.000Z",
        "created_at": "2024-01-27T12:55:00Z",
        "updated_at": "2024-01-27T13:00:00Z"
    },
    {
        "id": 183,
        "turbine_id": 98,
        "inspected_at": "2023-12-26T09:00:00.000Z",
        "created_at": "2024-01-27T12:55:00Z",
        "updated_at": "2024-01-27T13:00:00Z"
    },
    {
        "id": 184,
        "turbine_id": 98,
        "inspected_at": "2023-07-25T14:00:00.000Z",
        "created_at": "2024-01-27T12:55:00Z",
        "updated_at": "2024-01-27T13:00:00Z"
    },
    {
        "id": 185,
        "turbine_id": 99,
        "inspected_at": "2023-05-31T09:00:00.000Z",
        "created_at": "2024-01-27T12:55:00Z",
        "updated_at": "2024-01-27T13:00:00Z"
    },
    {
        "id": 186,
        "turbine_id": 99,
        "inspected_at": "2023-02-28T10:00:00.000Z",
        "created_at": "2024-01-27T12:55:00Z",
        "updated_at": "2024-01-27T13:00:00Z"
    },
    {
        "id": 187,
        "turbine_id": 100,
        "inspected_at": "2023-05-08T13:00:00.000Z",
        "created_at": "2024-01-27T12:55:00Z",
        "updated_at": "2024-01-27T13:00:00Z"
    },
    {
        "id": 188,
        "turbine_id": 100,
        "inspected_at": "2022-11-28T16:00:00.000Z",
        "created_at": "2024-01-27T12:55:00Z",
        "updated_at": "2024-01-27T13:00:00Z"
    },
    {
        "id": 189,
        "turbine_id": 101,
        "inspected_at": "2022-11-21T13:00:00.000Z",
        "created_at": "2024-01-27T12:55:00Z",
        "updated_at": "2024-01-27T13:00:00Z"
    },
    {
        "id": 190,
        "turbine_id": 101,
        "inspected_at": "2023-03-23T09:00:00.000Z",
        "created_at": "2024-01-27T12:55:00Z",
        "updated_at": "2024-01-27T13:00:00Z"
    },
    {
        "id": 191,
        "turbine_id": 101,
        "inspected_at": "2022-07-01T11:00:00.000Z",
        "created_at": "2024-01-27T12:55:00Z",
        "updated_at": "2024-01-27T13:00:00Z"
    },
    {
        "id": 192,
        "turbine_id": 102,
        "inspected_at": "2023-06-09T09:00:00.000Z",
        "created_at": "2024-01-27T12:55:00Z",
        "updated_at": "2024-01-27T13:00:00Z"
    },
    {
        "id": 193,
        "turbine_id": 102,
        "inspected_at": "2023-02-24T10:00:00.000Z",
        "created_at": "2024-01-27T12:55:00Z",
        "updated_at": "2024-01-27T13:00:00Z"
    },
    {
        "id": 194,
        "turbine_id": 102,
        "inspected_at": "2023-10-18T12:00:00.000Z",
        "created_at": "2024-01-27T12:55:00Z",
        "updated_at": "2024-01-27T13:00:00Z"
    },
    {
        "id": 195,
        "turbine_id": 103,
        "inspected_at": "2023-06-27T11:00:00.000Z",
        "created_at": "2024-01-27T12:55:00Z",
        "updated_at": "2024-01-27T13:00:00Z"
    },
    {
        "id": 196,
        "turbine_id": 104,
        "inspected_at": "2022-04-25T10:00:00.000Z",
        "created_at": "2024-01-27T12:55:00Z",
        "updated_at": "2024-01-27T13:00:00Z"
    },
    {
        "id": 197,
        "turbine_id": 104,
        "inspected_at": "2023-01-11T16:00:00.000Z",
        "created_at": "2024-01-27T12:55:00Z",
        "updated_at": "2024-01-27T13:00:00Z"
    },
    {
        "id": 198,
        "turbine_id": 105,
        "inspected_at": "2023-07-24T09:00:00.000Z",
        "created_at": "2024-01-27T12:55:00Z",
        "updated_at": "2024-01-27T13:00:00Z"
    },
    {
        "id": 199,
        "turbine_id": 105,
        "inspected_at": "2023-03-06T12:00:00.000Z",
        "created_at": "2024-01-27T12:55:00Z",
        "updated_at": "2024-01-27T13:00:00Z"
    },
    {
        "id": 200,
        "turbine_id": 105,
        "inspected_at": "2022-04-10T13:00:00.000Z",
        "created_at": "2024-01-27T12:55:00Z",
        "updated_at": "2024-01-27T13:00:00Z"
    },
    {
        "id": 201,
        "turbine_id": 106,
        "inspected_at": "2022-02-02T11:00:00.000Z",
        "created_at": "2024-01-27T12:55:00Z",
        "updated_at": "2024-01-27T13:00:00Z"
    },
    {
        "id": 202,
        "turbine_id": 107,
        "inspected_at": "2023-08-10T15:00:00.000Z",
        "created_at": "2024-01-27T12:55:00Z",
        "updated_at": "2024-01-27T13:00:00Z"
    },
    {
        "id": 203,
        "turbine_id": 107,
        "inspected_at": "2022-11-04T13:00:00.000Z",
        "created_at": "2024-01-27T12:55:00Z",
        "updated_at": "2024-01-27T13:00:00Z"
    },
    {
        "id": 204,
        "turbine_id": 107,
        "inspected_at": "2022-05-27T11:00:00.000Z",
        "created_at": "2024-01-27T12:55:00Z",
        "updated_at": "2024-01-27T13:00:00Z"
    },
    {
        "id": 205,
        "turbine_id": 108,
        "inspected_at": "2022-04-22T15:00:00.000Z",
        "created_at": "2024-01-27T12:55:00Z",
        "updated_at": "2024-01-27T13:00:00Z"
    },
    {
        "id": 206,
        "turbine_id": 108,
        "inspected_at": "2023-12-29T15:00:00.000Z",
        "created_at": "2024-01-27T12:55:00Z",
        "updated_at": "2024-01-27T13:00:00Z"
    }
]